LICENSE
MANIFEST.in
README.rst
setup.py
quicksect.egg-info/PKG-INFO
quicksect.egg-info/SOURCES.txt
quicksect.egg-info/dependency_links.txt
quicksect.egg-info/requires.txt
quicksect.egg-info/top_level.txt
src/quicksect.c
src/quicksect.pyx
tests/test_quicksect.py
tests/test_quicksect.pyc