Metadata-Version: 1.0
Name: quicksect
Version: 0.2.2
Summary: fast, simple interval intersection
Home-page: UNKNOWN
Author: Brent Pedersen
Author-email: bpederse@gmail.com
License: UNKNOWN
Platform: UNKNOWN
